sphinx_named_colors/__init__.py
sphinx_named_colors/_version.py
sphinx_named_colors-1.0.3.dist-info/METADATA
sphinx_named_colors-1.0.3.dist-info/WHEEL
sphinx_named_colors-1.0.3.dist-info/licenses/LICENSE
sphinx_named_colors-1.0.3.dist-info/RECORD
