Metadata-Version: 2.4
Name: sphinx-named-colors
Version: 1.0.3
Summary: A custom Sphinx extension to use CSS named colors and custom named colors in a Sphinx book
Author-email: Dennis den Ouden-van der Horst <d.denouden-vanderhorst@tudelft.nl>
License: MIT License
License-File: LICENSE
Requires-Python: >=3.10
Requires-Dist: numpy
Requires-Dist: sphinx
Requires-Dist: sphinxnotes-comboroles
